iemm/__init__.py
iemm/belief.py
iemm/core.py
iemm/utils.py
iemm-0.1.0.dist-info/licenses/LICENSE
iemm-0.1.0.dist-info/METADATA
iemm-0.1.0.dist-info/WHEEL
iemm-0.1.0.dist-info/top_level.txt
iemm-0.1.0.dist-info/RECORD
