Metadata-Version: 2.4
Name: iemm
Version: 0.1.0
Summary: Iterative Evidential Mistakeness Minimization - Explainable Evidential Clustering
Home-page: https://github.com/victorsouza89/iemm
Author: Victor Souza
Author-email: Victor Souza <victorflosouza@gmail.com>
Maintainer-email: Victor Souza <victorflosouza@gmail.com>
License-Expression: MIT
Project-URL: Homepage, https://github.com/victorsouza89/iemm
Project-URL: Repository, https://github.com/victorsouza89/iemm.git
Project-URL: Issues, https://github.com/victorsouza89/iemm/issues
Keywords: belief functions,evidential decision trees,machine learning,uncertainty
Classifier: Development Status :: 3 - Alpha
Classifier: Intended Audience :: Science/Research
Classifier: Operating System :: OS Independent
Classifier: Programming Language :: Python :: 3
Classifier: Programming Language :: Python :: 3.9
Classifier: Programming Language :: Python :: 3.10
Classifier: Programming Language :: Python :: 3.11
Classifier: Programming Language :: Python :: 3.12
Classifier: Programming Language :: Python :: 3.13
Classifier: Programming Language :: Python :: 3.14
Classifier: Programming Language :: Python :: 3.15
Classifier: Topic :: Scientific/Engineering :: Artificial Intelligence
Classifier: Topic :: Scientific/Engineering :: Mathematics
Requires-Python: >=3.8
License-File: LICENSE
Requires-Dist: numpy>=1.19.0
Requires-Dist: pandas>=1.2.0
Requires-Dist: scikit-learn>=0.24.0
Requires-Dist: schemdraw>=0.11
Dynamic: author
Dynamic: home-page
Dynamic: license-file
Dynamic: requires-python
